comics_mailer.py
comics_mailer-1.0.0.dist-info/DESCRIPTION.rst
comics_mailer-1.0.0.dist-info/METADATA
comics_mailer-1.0.0.dist-info/RECORD
comics_mailer-1.0.0.dist-info/WHEEL
comics_mailer-1.0.0.dist-info/entry_points.txt
comics_mailer-1.0.0.dist-info/metadata.json
comics_mailer-1.0.0.dist-info/top_level.txt
