Metadata-Version: 2.0
Name: comics-mailer
Version: 1.0.0
Summary: A comic release notifier using Mailgun.
Home-page: https://github.com/andreipoe/comics-mailer
Author: Andrei Poenaru
Author-email: andrei.poenaru@gmail.com
License: MIT
Keywords: comics notification mailgun
Platform: UNKNOWN
Classifier: Development Status :: 5 - Production/Stable
Classifier: Intended Audience :: End Users/Desktop
Classifier: Topic :: Utilities
Classifier: License :: OSI Approved :: MIT License
Classifier: Programming Language :: Python :: 3
Classifier: Programming Language :: Python :: 3.4
Classifier: Programming Language :: Python :: 3.5
Classifier: Programming Language :: Python :: 3.6
Requires-Python: >=3.4, <4
Requires-Dist: feedparser
Requires-Dist: beautifulsoup4
Requires-Dist: requests
Provides-Extra: dev
Requires-Dist: check-manifest; extra == 'dev'
Requires-Dist: pypandoc; extra == 'dev'
Provides-Extra: test
Requires-Dist: coverage; extra == 'test'
